inspector.py
sys_inspector/__init__.py
sys_inspector/bpf_programs.py
sys_inspector/report_generator.py
sys_inspector/sys_info.py
sys_inspector-0.30.9.dist-info/LICENSE.md
sys_inspector-0.30.9.dist-info/METADATA
sys_inspector-0.30.9.dist-info/WHEEL
sys_inspector-0.30.9.dist-info/entry_points.txt
sys_inspector-0.30.9.dist-info/top_level.txt
sys_inspector-0.30.9.dist-info/RECORD
