Metadata-Version: 2.1
Name: sys-inspector
Version: 0.30.9
Summary: eBPF-based System Inspector and Forensic Tool
Home-page: https://github.com/mariosergiosl/sys-inspector
Author: Mario Luz
Author-email: mario.mssl@gmail.com
License: UNKNOWN
Platform: UNKNOWN
Classifier: Programming Language :: Python :: 3
Classifier: License :: OSI Approved :: GNU General Public License v3 (GPLv3)
Classifier: Operating System :: POSIX :: Linux
Classifier: Topic :: System :: Systems Administration
Requires-Python: >=3.6
License-File: LICENSE.md
